LICENSE
MANIFEST.in
README.markdown
setup.cfg
setup.py
django_watson_nominus.egg-info/PKG-INFO
django_watson_nominus.egg-info/SOURCES.txt
django_watson_nominus.egg-info/dependency_links.txt
django_watson_nominus.egg-info/not-zip-safe
django_watson_nominus.egg-info/top_level.txt
watson/__init__.py
watson/admin.py
watson/backends.py
watson/middleware.py
watson/models.py
watson/search.py
watson/urls.py
watson/views.py
watson/management/__init__.py
watson/management/commands/__init__.py
watson/management/commands/buildwatson.py
watson/management/commands/installwatson.py
watson/management/commands/listwatson.py
watson/management/commands/uninstallwatson.py
watson/migrations/0001_initial.py
watson/migrations/__init__.py
watson/templates/watson/search_results.html
watson/templates/watson/includes/search_result_item.html
watson/templates/watson/includes/search_results.html
watson/templatetags/__init__.py
watson/templatetags/watson.py