Metadata-Version: 2.1
Name: django-watson-nominus
Version: 1.5.5
Summary: Full-text multi-table search application for Django. Easy to install and use, with good performance.
Home-page: http://github.com/madchap/django-watson
Author: Dave Hall
Author-email: dave@etianen.com
License: UNKNOWN
Platform: UNKNOWN
Classifier: Development Status :: 5 - Production/Stable
Classifier: Environment :: Web Environment
Classifier: Intended Audience :: Developers
Classifier: License :: OSI Approved :: BSD License
Classifier: Operating System :: OS Independent
Classifier: Programming Language :: Python
Classifier: Programming Language :: Python :: 3.6
Classifier: Programming Language :: Python :: 3.7
Classifier: Programming Language :: Python :: 3.8
Classifier: Framework :: Django
